Metadata-Version: 2.4
Name: llama-index-vector-stores-lantern
Version: 0.4.1
Summary: llama-index vector_stores lantern integration
Author-email: Your Name <you@example.com>
License-Expression: MIT
License-File: LICENSE
Requires-Python: <4.0,>=3.9
Requires-Dist: asyncpg<0.31,>=0.30.0
Requires-Dist: llama-index-core<0.15,>=0.13.0
Requires-Dist: psycopg2-binary<3,>=2.9.9
Requires-Dist: sqlalchemy[asyncio]<3,>=2.0.25
